xy_type/__init__.py
xy_type/utils.py
xy_type-1.0.8.dist-info/LICENSE
xy_type-1.0.8.dist-info/METADATA
xy_type-1.0.8.dist-info/WHEEL
xy_type-1.0.8.dist-info/top_level.txt
xy_type-1.0.8.dist-info/RECORD
